jagular/__init__.py
jagular/alignment.py
jagular/deprecated.py
jagular/examples.py
jagular/filtering.py
jagular/io.py
jagular/readers.py
jagular/signal.py
jagular/spikes.py
jagular/utils.py
jagular/version.py
jagular-0.0.2.dist-info/LICENSE.rst
jagular-0.0.2.dist-info/METADATA
jagular-0.0.2.dist-info/WHEEL
jagular-0.0.2.dist-info/top_level.txt
jagular-0.0.2.dist-info/RECORD
