Metadata-Version: 2.1
Name: jagular
Version: 0.0.2
Summary: Out-of-core pre-processing of big-ish electrophysiology data.
Home-page: https://github.com/kemerelab/jagular/
Author: Joshua Chu, Etienne Ackermann
Author-email: jpc6@rice.edu
License: MIT License
Download-URL: https://github.com/kemerelab/jagular/tarball/0.0.2
Keywords: electrophysiology neuroscience data analysis
Platform: any
Requires-Dist: numpy (>=1.9.0)
Requires-Dist: scipy (>=0.18.0)
